pmdb_utils/__init__.py
pmdb_utils/api_related.py
pmdb_utils/key_vault_client.py
pmdb_utils/dataacceslayer/__init__.py
pmdb_utils/dataacceslayer/enum_config.py
pmdb_utils/dataacceslayer/stagewriterhelper.py
pmdb_utils/dataacceslayer/storageclient.py
pmdb_utils/dataacceslayer/storageoptions.py
pmdb_utils/dataacceslayer/utils.py
pmdb_utils/metadata/__init__.py
pmdb_utils/metadata/metadatagenerator.py
pmdb_utils/metadata/metareader.py
pmdb_utils/metadata/utils.py
pmdb_utils-0.5.51.dist-info/METADATA
pmdb_utils-0.5.51.dist-info/WHEEL
pmdb_utils-0.5.51.dist-info/entry_points.txt
pmdb_utils-0.5.51.dist-info/RECORD
