Metadata-Version: 2.4
Name: pmdb_utils
Version: 0.5.51
Summary: A utilities package for poorman-dataplatform
Author-email: saebod <saebod@hotmail.com>
Requires-Python: >=3.9
Requires-Dist: azure-identity>=1.25.0
Requires-Dist: azure-keyvault>=4.2.0
Requires-Dist: bump-my-version>=1.2.5
Requires-Dist: minio>=7.2.16
Requires-Dist: polars-lts-cpu>=1.33.1
Requires-Dist: python-dotenv>=1.1.1
